docs/_downloads/29a3c68eabc4dfce3cc2b8f28cbf7499/test.py
docs/_downloads/9a3170560eff0e8080a7006943761820/PubSubTs.template.py
docs/_downloads/a8af61e20b3888c79a5cc6ff79c43632/HelloWorldPy.template.py
docs/_downloads/cb75f7c5c4638fa0c1e352dc3e3ce4c7/HelloWorldTs.template.py
docs/build/_downloads/29a3c68eabc4dfce3cc2b8f28cbf7499/test.py
docs/build/_downloads/9a3170560eff0e8080a7006943761820/PubSubTs.template.py
docs/build/_downloads/a8af61e20b3888c79a5cc6ff79c43632/HelloWorldPy.template.py
docs/build/_downloads/cb75f7c5c4638fa0c1e352dc3e3ce4c7/HelloWorldTs.template.py
docs/build/html/_downloads/29a3c68eabc4dfce3cc2b8f28cbf7499/test.py
docs/build/html/_downloads/9a3170560eff0e8080a7006943761820/PubSubTs.template.py
docs/build/html/_downloads/a8af61e20b3888c79a5cc6ff79c43632/HelloWorldPy.template.py
docs/build/html/_downloads/cb75f7c5c4638fa0c1e352dc3e3ce4c7/HelloWorldTs.template.py
docs/source/conf.py
webezyio/__init__.py
webezyio/__version__.py
webezyio/config.py
webezyio/architect/__init__.py
webezyio/architect/commands.py
webezyio/architect/hooks.py
webezyio/architect/invoker.py
webezyio/architect/interfaces/__init__.py
webezyio/architect/recievers/__init__.py
webezyio/builder/__init__.py
webezyio/builder/plugins/WebezyBase.py
webezyio/builder/plugins/WebezyDocker.py
webezyio/builder/plugins/WebezyGoClient.py
webezyio/builder/plugins/WebezyGoServer.py
webezyio/builder/plugins/WebezyMigrate.py
webezyio/builder/plugins/WebezyMonitor.py
webezyio/builder/plugins/WebezyProto.py
webezyio/builder/plugins/WebezyProxy.py
webezyio/builder/plugins/WebezyPyClient.py
webezyio/builder/plugins/WebezyPyServer.py
webezyio/builder/plugins/WebezyReadme.py
webezyio/builder/plugins/WebezyTsClient.py
webezyio/builder/plugins/WebezyTsServer.py
webezyio/builder/plugins/WebezyWebpack.py
webezyio/builder/plugins/__init__.py
webezyio/builder/plugins/static.py
webezyio/builder/src/__init__.py
webezyio/builder/src/hookspecs.py
webezyio/builder/src/lru.py
webezyio/builder/src/main.py
webezyio-0.1.9.dist-info/LICENSE
webezyio-0.1.9.dist-info/METADATA
webezyio-0.1.9.dist-info/WHEEL
webezyio-0.1.9.dist-info/entry_points.txt
webezyio-0.1.9.dist-info/top_level.txt
webezyio-0.1.9.dist-info/RECORD
