Metadata-Version: 2.1
Name: webezyio
Version: 0.1.9
Summary: Webezy.io CLI for generating gRPC micro-services
Author-email: Amit Shmulevitch <amitsh1995@gmail.com>
License: Copyright (c) 2022 Webezy.io.
Project-URL: repository, https://github.com/Webezy-io/webezyio
Project-URL: homepage, https://www.webezy.io/
Project-URL: documentation, https://www.webezy.io/docs/cli
Keywords: grpc,micro-services,cli,framework
Classifier: License :: OSI Approved :: MIT License
Classifier: Programming Language :: Python
Classifier: Programming Language :: Python :: 3
Requires-Python: >=3.7
License-File: LICENSE
Requires-Dist: pluggy (<1.0,>=0.3)
Requires-Dist: inquirer
Requires-Dist: prettytable
Requires-Dist: protobuf (<=4.21.6)
Requires-Dist: grpcio (==1.47.0)
Requires-Dist: grpcio-tools (==1.47.0)
Provides-Extra: build
Requires-Dist: build ; extra == 'build'
Requires-Dist: twine ; extra == 'build'
Provides-Extra: dev
Requires-Dist: bumpver ; extra == 'dev'
